cuvisoft/__init__.py
cuvisoft-0.1.dist-info/LICENCE.txt
cuvisoft-0.1.dist-info/METADATA
cuvisoft-0.1.dist-info/WHEEL
cuvisoft-0.1.dist-info/top_level.txt
cuvisoft-0.1.dist-info/RECORD
