Metadata-Version: 2.1
Name: cuvisoft
Version: 0.1
Summary: this bassic calculator
Home-page: UNKNOWN
Author: Balaji
Author-email: cuvisoft@gmail.com
License: UNKNOWN
Platform: UNKNOWN
Classifier: Programming Language :: Python :: 3
Classifier: License :: OSI Approved :: MIT License
Classifier: Operating System :: OS Independent
License-File: LICENCE.txt
